easy_acumatica/__init__.py
easy_acumatica/batch.py
easy_acumatica/client.py
easy_acumatica/config.py
easy_acumatica/core.py
easy_acumatica/exceptions.py
easy_acumatica/generate_stubs.py
easy_acumatica/helpers.py
easy_acumatica/inquiries.py
easy_acumatica/model_factory.py
easy_acumatica/models.py
easy_acumatica/odata.py
easy_acumatica/py.typed
easy_acumatica/service_factory.py
easy_acumatica/utils.py
easy_acumatica/scheduler/__init__.py
easy_acumatica/scheduler/builder.py
easy_acumatica/scheduler/core.py
easy_acumatica/scheduler/decorators.py
easy_acumatica/scheduler/persistence.py
easy_acumatica/scheduler/schedules.py
easy_acumatica/scheduler/task.py
easy_acumatica/scheduler/utils.py
easy_acumatica-0.5.10.dist-info/licenses/LICENSE
easy_acumatica-0.5.10.dist-info/METADATA
easy_acumatica-0.5.10.dist-info/WHEEL
easy_acumatica-0.5.10.dist-info/entry_points.txt
easy_acumatica-0.5.10.dist-info/top_level.txt
easy_acumatica-0.5.10.dist-info/RECORD
