Metadata-Version: 2.4
Name: easy_acumatica
Version: 0.5.10
Summary: Python wrapper for the Acumatica REST API
Author-email: Matthew Hirstius <matthew.c.hirstius@gmail.com>
License: MIT
Project-URL: Homepage, https://www.easyacumatica.com/
Project-URL: Source, https://github.com/Nioron07/Easy-Acumatica
Project-URL: Documentation, https://easyacumatica.com/python
Project-URL: Bug Tracker, https://github.com/Nioron07/Easy-Acumatica/issues
Keywords: acumatica,erp,api,rest,client
Classifier: Development Status :: 4 - Beta
Classifier: Intended Audience :: Developers
Classifier: License :: OSI Approved :: MIT License
Classifier: Operating System :: OS Independent
Classifier: Programming Language :: Python :: 3
Classifier: Programming Language :: Python :: 3.8
Classifier: Programming Language :: Python :: 3.9
Classifier: Programming Language :: Python :: 3.10
Classifier: Programming Language :: Python :: 3.11
Classifier: Programming Language :: Python :: 3.12
Classifier: Programming Language :: Python :: 3.13
Classifier: Programming Language :: Python :: 3.14
Classifier: Topic :: Software Development :: Libraries :: Python Modules
Classifier: Topic :: Office/Business :: Financial :: Accounting
Classifier: Typing :: Typed
Requires-Python: >=3.8
License-File: LICENSE
Requires-Dist: requests<3.0.0,>=2.25.1
Requires-Dist: aiohttp<4.0.0,>=3.8.0
Requires-Dist: typing-extensions>=4.0.0; python_version < "3.10"
Requires-Dist: croniter>=1.3.0
Provides-Extra: dev
Requires-Dist: pytest>=7.0.0; extra == "dev"
Requires-Dist: pytest-cov>=4.0.0; extra == "dev"
Requires-Dist: pytest-mock>=3.0.0; extra == "dev"
Requires-Dist: requests-mock>=1.9.0; extra == "dev"
Requires-Dist: flask>=2.0.0; extra == "dev"
Requires-Dist: types-requests; extra == "dev"
Provides-Extra: scheduler
Requires-Dist: APScheduler>=3.10.0; extra == "scheduler"
Dynamic: license-file
